rcon/__init__.py
rcon/client.py
rcon/config.py
rcon/console.py
rcon/errorhandler.py
rcon/exceptions.py
rcon/gui.py
rcon/rconclt.py
rcon/rconshell.py
rcon/readline.py
rcon/battleye/__init__.py
rcon/battleye/client.py
rcon/battleye/proto.py
rcon/source/__init__.py
rcon/source/async_rcon.py
rcon/source/client.py
rcon/source/proto.py
rcon-2.4.6.dist-info/LICENSE.txt
rcon-2.4.6.dist-info/METADATA
rcon-2.4.6.dist-info/WHEEL
rcon-2.4.6.dist-info/entry_points.txt
rcon-2.4.6.dist-info/top_level.txt
rcon-2.4.6.dist-info/RECORD
