Metadata-Version: 2.1
Name: rcon
Version: 2.4.6
Summary: An RCON client library.
Home-page: https://github.com/conqp/rcon
Author: Richard Neumann
Author-email: mail@richard-neumann.de
License: GPLv3
Keywords: python rcon client
Requires-Python: >=3.10
License-File: LICENSE.txt
Provides-Extra: gui
Requires-Dist: pygobject; extra == "gui"
Requires-Dist: pygtk; extra == "gui"
